mandrill.py
mandrill_erichurkman-1.0.58.data/scripts/mandrill
mandrill_erichurkman-1.0.58.data/scripts/sendmail.mandrill
mandrill_erichurkman-1.0.58.dist-info/METADATA
mandrill_erichurkman-1.0.58.dist-info/RECORD
mandrill_erichurkman-1.0.58.dist-info/WHEEL
mandrill_erichurkman-1.0.58.dist-info/top_level.txt
