Metadata-Version: 2.1
Name: mandrill-erichurkman
Version: 1.0.58
Summary: A CLI client and Python API library for the Mandrill email as a service platform.
Home-page: https://github.com/erichurkman/mandrill-api-python
Author: Mandrill Devs
Author-email: erichurkman@gmail.com
License: Apache-2.0
Keywords: mandrill email api
Platform: UNKNOWN
Classifier: Development Status :: 4 - Beta
Classifier: Environment :: Console
Classifier: Intended Audience :: Developers
Classifier: Intended Audience :: System Administrators
Classifier: License :: OSI Approved :: Apache Software License
Classifier: Topic :: Communications :: Email
Requires-Dist: requests (>=0.13.2)
Requires-Dist: docopt (==0.4.0)
